rtl/alu.v
`timescale 1ns/100ps

// Functional Units Setup..............


/* ==================================================================
Function: FORWARD
Description: Forwards DATA2 into RESULT
Supported Instructions: loadi, move
SELECT Input: 000
Unit's Delay: #1
*/

module forward_unit (
    // required input output setup
    input  wire [7:0] DATA2,
    output reg  [7:0] RESULT
);
    // Get triggered whenever DATA2 changes
    always @(DATA2)
    begin
        #1 RESULT = DATA2; 
        // Artificial delay of 1 time unit
    end
endmodule

/*====================================================================
Function: ADD
Description: Adds DATA1 and DATA2.
Supported Instructions: add, sub
SELECT Input: 001
Unit's Delay: #2
*/

module add_unit (
    // required input output setup
    input  wire [7:0] DATA1,
    input  wire [7:0] DATA2,
    output reg  [7:0] RESULT
);
    // Execute whenever operands DATA1 or DATA2 get change
    always @(DATA1 or DATA2)
    begin
        #2 RESULT = DATA1 + DATA2;
        // Artificial delay of 2 time units as required
    end
endmodule


/* =====================================================================
Function: AND
Description: Performs bitwise AND on DATA1 and DATA2.
Supported Instructions: and
SELECT Input: 010
Unit's Delay: #1
*/

module and_unit (
    // required input output setup
    input  wire [7:0] DATA1,
    input  wire [7:0] DATA2,
    output reg  [7:0] RESULT
);
    // Execute whenever operands DATA1 or DATA2 get change
    always @(DATA1 or DATA2)
    begin
        #1 RESULT = DATA1 & DATA2;
        // Artificial delay of 1 time unit
    end
endmodule

/* ====================================================================
Function: OR
Description: Performs bitwise OR on DATA1 and DATA2
Supported Instructions: or
SELECT Input: 011
Unit's Delay: #1
*/

module or_unit (
    input  wire [7:0] DATA1,
    input  wire [7:0] DATA2,
    output reg  [7:0] RESULT
);
    // Execute whenever operands DATA1 or DATA2 get change
    always @(DATA1 or DATA2)
    begin
        #1 RESULT = DATA1 | DATA2;
        // Artificial delay of 1 time unit
    end
endmodule


// ==================================================================
// New Unit: Multiplier (Shift & Add Array)
// Shifting units not used 
// using wire by wire concatanate instaed of shifting
// Delay: #2
// ==================================================================
module mult_unit (
    input  wire [7:0] DATA1,
    input  wire [7:0] DATA2,
    output reg  [7:0] RESULT
);
    wire [7:0] p0, p1, p2, p3, p4, p5, p6, p7;
    
    assign p0 = DATA2[0] ? DATA1 : 8'd0;
    assign p1 = DATA2[1] ? {DATA1[6:0], 1'b0} : 8'd0;
    assign p2 = DATA2[2] ? {DATA1[5:0], 2'b00} : 8'd0;
    assign p3 = DATA2[3] ? {DATA1[4:0], 3'b000} : 8'd0;
    assign p4 = DATA2[4] ? {DATA1[3:0], 4'b0000} : 8'd0;
    assign p5 = DATA2[5] ? {DATA1[2:0], 5'b00000} : 8'd0;
    assign p6 = DATA2[6] ? {DATA1[1:0], 6'b000000} : 8'd0;
    assign p7 = DATA2[7] ? {DATA1[0], 7'b0000000} : 8'd0;

    always @(DATA1 or DATA2) begin
        #2 RESULT = p0 + p1 + p2 + p3 + p4 + p5 + p6 + p7;
    end
endmodule

// ==================================================================
// New Unit: Universal Shifter (SLL, SRL, SRA, ROR)
// Delay: #1
// ==================================================================
module shift_unit (
    input  wire [7:0] DATA1,
    input  wire [7:0] DATA2,
    input  wire [1:0] SHIFT_SEL,
    output reg  [7:0] RESULT
);
    wire [2:0] shamt = DATA2[2:0];

    // Left Shift
    wire [7:0] sl1 = shamt[0] ? {DATA1[6:0], 1'b0} : DATA1;
    wire [7:0] sl2 = shamt[1] ? {sl1[5:0], 2'b00} : sl1;
    wire [7:0] sl3 = shamt[2] ? {sl2[3:0], 4'b0000} : sl2;

    // Logical Right Shift
    wire [7:0] sr1 = shamt[0] ? {1'b0, DATA1[7:1]} : DATA1;
    wire [7:0] sr2 = shamt[1] ? {2'b00, sr1[7:2]} : sr1;
    wire [7:0] sr3 = shamt[2] ? {4'b0000, sr2[7:4]} : sr2;

    // Arithmetic Right Shift
    wire [7:0] sa1 = shamt[0] ? {DATA1[7], DATA1[7:1]} : DATA1;
    wire [7:0] sa2 = shamt[1] ? {{2{sa1[7]}}, sa1[7:2]} : sa1;
    wire [7:0] sa3 = shamt[2] ? {{4{sa2[7]}}, sa2[7:4]} : sa2;

    // Rotate Right
    wire [7:0] ro1 = shamt[0] ? {DATA1[0], DATA1[7:1]} : DATA1;
    wire [7:0] ro2 = shamt[1] ? {ro1[1:0], ro1[7:2]} : ro1;
    wire [7:0] ro3 = shamt[2] ? {ro2[3:0], ro2[7:4]} : ro2;

    always @(*) begin
        #1; 
        case (SHIFT_SEL)
            2'b00: RESULT = sl3; // SLL
            2'b01: RESULT = sr3; // SRL
            2'b10: RESULT = sa3; // SRA
            2'b11: RESULT = ro3; // ROR
        endcase
    end
endmodule

// Top level module alu setup..........
module alu (
    input  wire [7:0] DATA1,
    input  wire [7:0] DATA2,
    output reg  [7:0] RESULT,
    output reg        ZERO,
    input  wire [2:0] SELECT,
    input  wire [1:0] SHIFT_SEL
);  
    // Wires to hold the output results from each functional module unit
    wire [7:0] forward_res, add_res, and_res, or_res, mult_res, shift_res;

    // Instantion of functional units implemented above, as required
    forward_unit fu  (.DATA2(DATA2), .RESULT(forward_res));
    add_unit     au  (.DATA1(DATA1), .DATA2(DATA2), .RESULT(add_res));
    and_unit     andu(.DATA1(DATA1), .DATA2(DATA2), .RESULT(and_res));
    or_unit      ou  (.DATA1(DATA1), .DATA2(DATA2), .RESULT(or_res));
    mult_unit    mu  (.DATA1(DATA1), .DATA2(DATA2), .RESULT(mult_res));
    shift_unit   su  (.DATA1(DATA1), .DATA2(DATA2), .SHIFT_SEL(SHIFT_SEL), .RESULT(shift_res));

    // MUX implementation for SELECT lines
    always @(*) begin

         // By using a case structure
        case (SELECT)
            3'b000:  RESULT = forward_res;
            3'b001:  RESULT = add_res;
            3'b010:  RESULT = and_res;
            3'b011:  RESULT = or_res;
            3'b100:  RESULT = mult_res;
            3'b101:  RESULT = shift_res;
            default: RESULT = 8'b00000000;
        endcase
        
        // Update the ZERO flag dynamically 
        if (RESULT == 8'b00000000)
            ZERO = 1'b1;
        else
            ZERO = 1'b0;
    end
endmodule

rtl/cpu.v
`timescale 1ns/100ps


// ------------------------------------------------------------
// Control Unit 

/* ==================================================================
Unit: control_unit
Description: According to the given OPCODE,
            Outputs ALU operation code,
            WRite Enable signal,
            Immediate, 2s complement selector 
*/

module control_unit (
    input  wire [7:0] OPCODE,
    output reg [2:0] ALUOP,
    output reg WRITEENABLE,
    output reg IMM_SEL,  
    output reg NEG_SEL,
    output reg JUMP,        // Flag for Jump instruction
    output reg BRANCH_EQ,   // Flag for Branch if equal instruction
    output reg BRANCH_NEQ,  // // Flag for Branch if not equal instruction
    output reg [1:0] SHIFT_SEL 
);

    // Instruction Opcodes saved as local parameters
    // Values configured according to the Assembler ISA
    localparam OP_LOADI = 8'b00000000;
    localparam OP_MOV   = 8'b00000001;
    localparam OP_ADD   = 8'b00000010;
    localparam OP_SUB   = 8'b00000011;
    localparam OP_AND   = 8'b00000100;
    localparam OP_OR    = 8'b00000101;

    // J anf beq
    localparam OP_J     = 8'b00000110;  
    localparam OP_BEQ   = 8'b00000111;

    // for the extended ISA
    localparam OP_MULT  = 8'b00001000;
    localparam OP_SLL   = 8'b00001001;
    localparam OP_SRL   = 8'b00001010;
    localparam OP_SRA   = 8'b00001011;
    localparam OP_ROR   = 8'b00001100;
    localparam OP_BNE   = 8'b00001101;


     // Control Unit Operations
    always @(OPCODE) begin

        #1;  // Artificial decode delay    
        
        // Setting up output according to the OPCODE Input ------------

        // Defaults establishing
        ALUOP       = 3'b000;
        WRITEENABLE = 1'b0;
        IMM_SEL     = 1'b0;
        NEG_SEL     = 1'b0;
        JUMP        = 1'b0;
        BRANCH_EQ   = 1'b0;
        BRANCH_NEQ  = 1'b0;
        SHIFT_SEL   = 2'b00;

        // Used case base setup
        case (OPCODE)
        
            OP_LOADI: begin ALUOP = 3'b000; WRITEENABLE = 1'b1; IMM_SEL = 1'b1; end
            OP_MOV:   begin ALUOP = 3'b000; WRITEENABLE = 1'b1; end
            OP_ADD:   begin ALUOP = 3'b001; WRITEENABLE = 1'b1; end
            OP_SUB:   begin ALUOP = 3'b001; WRITEENABLE = 1'b1; NEG_SEL = 1'b1; end
            OP_AND:   begin ALUOP = 3'b010; WRITEENABLE = 1'b1; end
            OP_OR:    begin ALUOP = 3'b011; WRITEENABLE = 1'b1; end

            // J and beq
            OP_J:     begin JUMP  = 1'b1; end
            OP_BEQ:   begin ALUOP = 3'b001; NEG_SEL = 1'b1; BRANCH_EQ = 1'b1; end
            
            // new extended ISA
            OP_MULT:  begin ALUOP = 3'b100; WRITEENABLE = 1'b1; end
            OP_SLL:   begin ALUOP = 3'b101; WRITEENABLE = 1'b1; IMM_SEL = 1'b1; SHIFT_SEL = 2'b00; end
            OP_SRL:   begin ALUOP = 3'b101; WRITEENABLE = 1'b1; IMM_SEL = 1'b1; SHIFT_SEL = 2'b01; end
            OP_SRA:   begin ALUOP = 3'b101; WRITEENABLE = 1'b1; IMM_SEL = 1'b1; SHIFT_SEL = 2'b10; end
            OP_ROR:   begin ALUOP = 3'b101; WRITEENABLE = 1'b1; IMM_SEL = 1'b1; SHIFT_SEL = 2'b11; end
            OP_BNE:   begin ALUOP = 3'b001; NEG_SEL = 1'b1; BRANCH_NEQ = 1'b1; end
        endcase        
    end
endmodule


/* ==================================================================
Unit: twos_comp
Description: provide 2's complement for an INPUT
Unit's Delay: 1
*/

module twos_comp (
    input  wire [7:0] DATA,
    output reg  [7:0] RESULT
);
    always @(DATA) begin
        #1 RESULT = ~DATA + 8'b00000001;
    end
endmodule


/* ==================================================================
Unit: pc_adder
Description: register which points to the next instruction.
Initially 0 and resets to 0 at RESET signal
Unit's Delay: 1 delat for write to PC register
*/

module pc_adder (
    input  wire [31:0] PC_IN,
    output reg  [31:0] PC_NEXT
);
    always @(PC_IN) begin
        #1 PC_NEXT = PC_IN + 32'd4;
    end
endmodule


/* =================================================================
Unit: bj_adder
Description: branch or jump target adder
Computes target relative to PC_NEXT
Unit's Delay: #2 latency
*/

module bj_adder (
    input  wire [31:0] PC_NEXT,
    input  wire [31:0] OFFSET,
    output reg  [31:0] TARGET
);
    always @(PC_NEXT or OFFSET) begin
        #2 TARGET = PC_NEXT + OFFSET;
    end
endmodule





// ------------------------------------------------------------
// Unit: Top-Level CPU Module
// module cpu(PC, INSTRUCTION, CLK, RESET)
//

module cpu (
    output reg  [31:0] PC,          
    input  wire [31:0] INSTRUCTION, 
    input  wire CLK,
    input  wire RESET
);

    // Slicing of Instruction
    wire [7:0] opcode = INSTRUCTION[31:24];
    wire [2:0] rd     = INSTRUCTION[18:16]; 
    wire [7:0] imm    = INSTRUCTION[7:0];

    // Extracting the offset in RD,IMM field
    // bits 23:16
    wire [7:0] offset_imm = INSTRUCTION[23:16];
    
    // Wires for register reading
    reg [2:0] read_reg1_addr;
    reg [2:0] read_reg2_addr;
    
    // ALU Operaion signal
    wire [2:0] aluop;

    // Control Unit Signals
    wire writeenable;
    wire imm_sel;
    wire neg_sel;
    wire jump;
    wire branch_eq;
    wire branch_neq;
    wire [1:0] shift_sel;

    // Connections in Datapath
    wire [7:0] regout1;   
    wire [7:0] regout2;   
    wire [7:0] twos_result;
    wire [31:0] pc_next;
    wire [7:0] alu_result;
    wire zero; 

    reg [7:0] mux_sub_out;
    reg [7:0] alu_data2;

    // Branch and Jump calculations adder related
    wire [31:0] bj_target;

    wire pc_src;

    // Sign extend 8 bit offset
    // Then shift left by 2 = multiply by 4 (instruction size)
    wire [31:0] extended_offset;

    assign extended_offset = {{22{offset_imm[7]}}, offset_imm, 2'b00};


    // ----------------------------------------------------------
    // Adresses of two Read registers parsing according to instruction type
    // done based on OPCODE
    always @(*) begin
        // For MOV instructions
        // localparam OP_MOV   = 8'b00000001;
        if (opcode == 8'b00000001) begin
            read_reg1_addr = INSTRUCTION[2:0];  // Source register from Byte 0
            read_reg2_addr = 3'b000;            // for fault tollerence rather than keeping floating

        // Other instructions - ADD, SUB, AND, OR 
        end else begin
            read_reg1_addr = INSTRUCTION[10:8];
            read_reg2_addr = INSTRUCTION[2:0];
        end
    end

    // Creating instants of each submodule

    // control unit
    control_unit cu (
        .OPCODE (opcode),
        .ALUOP (aluop),
        .WRITEENABLE (writeenable),
        .IMM_SEL (imm_sel),
        .NEG_SEL (neg_sel),
        .JUMP (jump),
        .BRANCH_EQ (branch_eq),
        .BRANCH_NEQ (branch_neq),
        .SHIFT_SEL (shift_sel)
    );

    // register file
    reg_file rf (
        .IN (alu_result),
        .OUT1 (regout1),
        .OUT2 (regout2),
        .INADDRESS (rd),
        .OUT1ADDRESS (read_reg1_addr), 
        .OUT2ADDRESS (read_reg2_addr), 
        .WRITE (writeenable),
        .CLK (CLK),
        .RESET (RESET)
    );


    twos_comp tc (
        .DATA (regout2),
        .RESULT (twos_result)
    );

    // PC adder unit
    pc_adder pca (
        .PC_IN (PC),
        .PC_NEXT (pc_next)
    );

    // branch control unit
    bj_adder bja (
        .PC_NEXT (pc_next),
        .OFFSET (extended_offset),
        .TARGET (bj_target)
    );

    // ALU
    alu main_alu (
        .DATA1 (regout1),
        .DATA2 (alu_data2),
        .RESULT (alu_result),
        .ZERO (zero),       
        .SELECT(aluop),
        .SHIFT_SEL(shift_sel)
    );


// Additional MUXes needed

/* ==================================================================
Unit: MUX
Description: select 8 bit selection based on a control signal
CONTROL SIGNAL: 0 / 1
Unit's Delay: 0
*/

    // MUX 1: 2's Complement Selection
    always @(*) begin
        if (neg_sel)
            mux_sub_out = twos_result;
        else
            mux_sub_out = regout2;
    end

    // MUX 2: Immediate Selection
    always @(*) begin
        if (imm_sel)
            alu_data2 = imm;
        else
            alu_data2 = mux_sub_out;
    end

    // Updated PC Multiplexer Logic
    assign pc_src = jump | (branch_eq & zero) | (branch_neq & ~zero);

    // PC Update Logic
    // Happens according to Synchronous CLK
    // PC update delay is present
    always @(posedge CLK) begin
        if (RESET)
            #1 PC <= 32'b0;
        else if (pc_src)
            #1 PC <= bj_target;      // PC overwritten by calculated target
        else
            #1 PC <= pc_next;     // Standard sequence
    end
endmodule

src/Register File/reg_file.v
// Setting up the time step
`timescale 1ns/100ps

/*
Module: reg_file
Description: 8x8 Register File:
             1 synchronous write port
             2 asynchronous read ports
*/

module reg_file (

    //input output port setup
    input  wire [7:0] IN,
    output reg  [7:0] OUT1,
    output reg  [7:0] OUT2,
    input  wire [2:0] INADDRESS,
    input  wire [2:0] OUT1ADDRESS,
    input  wire [2:0] OUT2ADDRESS,
    input  wire WRITE,
    input  wire CLK,
    input  wire RESET
);


    // Register Storage Declaration
    reg [7:0] registers [0:7];
    
    // Iterator as a helper for reset loops
    integer i;


    // Write and Reset triggeres on the positive edge of the clock
    always @(posedge CLK) 
    begin
        if (RESET) begin  // if RESET is 1
        
            #1;  // Used delay for realistic latency
            for (i = 0; i < 8; i = i + 1)
            begin
                // Synchronous reset: clear all registers to 0
                registers[i] <= 8'b00000000;
            end
        end 
        
        else if (WRITE) begin
            // load IN data to specified INADDRESS with a #1 delay
            // Synchronus writing is used
            #1 registers[INADDRESS] <= IN;
            // Used delay for realistic latency
        end
    end



    // Read Logic for Outputs
    // Asynchronus
    // Updates whenever the address or target register data changes
    always @(*)
    begin
    // Artificial delay of 2 time units for realistic reading latency
    #2;
    OUT1 = registers[OUT1ADDRESS];
    OUT2 = registers[OUT2ADDRESS];
    end

endmodule

testbench/cpu_tb.v
// ============================================================================
// CO2070 Computer Architecture
// cpu_tb.v

`timescale 1ns/100ps

module cpu_tb;

    // Input /Output setup for CPU
    reg CLK;
    reg RESET;
    wire [31:0] PC;
    wire [31:0] INSTRUCTION;


    // Array for instructions
    reg [7:0] instr_mem [0:1023];
    integer i;

    // Asynchronously Reading Instructions from memory
    // With a latency of #2 
    assign #2 INSTRUCTION = {instr_mem[PC+3], instr_mem[PC+2], instr_mem[PC+1], instr_mem[PC]};

    // CPU Module Instance
    cpu mycpu (
        .PC(PC),
        .INSTRUCTION(INSTRUCTION),
        .CLK(CLK),
        .RESET(RESET)
    );

    // ---------------------------------------------------------------------
    // Clock Generator
    // Period of 8 ns
    initial CLK = 1'b1;
    always #4 CLK = ~CLK;

    // Main Driver Simulation
    initial
    begin
        $dumpfile("cpu_wavedata.vcd");
        $dumpvars(0, cpu_tb);

        CLK   = 1'b0;
        RESET = 1'b0; 

        // Force populate memory cells
        // Alternative NOP operations as 8'hFF
        // Used to stop WRITEENABLE getting stuck in High specially during empty cycles
        for (i = 0; i < 1024; i = i + 1) begin
            instr_mem[i] = 8'hFF; 
        end

        // Read compiled program file
        $readmemb("instr_mem.mem", instr_mem);
        #1; // Hardware cell stabilization window


        // ------------------------------------------------------------------------------------------------------------------
        // An Initial Hardware Reset was implemented for better clarity 
        // Hold through one full clock cycle period before beginning executions
        RESET = 1'b1;
        #4;

        // Value down at Negative CLK edge
        @(negedge CLK);
        RESET = 1'b0;

        // Run long enough to fully execute all 6 assembly lines
        // Suitable run time setup
        #120;



        // ############################################################################################
        /*
        Tested Instruction Set
            loadi 1 0xB6
            loadi 2 0x6D
            and 3 1 2
            or 4 1 2
            add 5 4 1
            mov 6 3
            sub 4 5 2
        */
        // ###############################################################################################
        $finish;
    end

    // Signal Tracing Monitor Terminal Output
    initial
    begin
        $monitor("Time=%0t ns | PC=%0d | Instr=0x%h | ALU_Out=0x%h | RegWriteEnable=%b",
         $time, PC, INSTRUCTION, mycpu.alu_result, mycpu.writeenable);
    end

endmodule

simulation/waves/cpu_wavedata.vcd
$date
	Thu Jun 18 09:19:13 2026
$end
$version
	Icarus Verilog
$end
$timescale
	100ps
$end
$scope module cpu_tb $end
$var wire 32 ! PC [31:0] $end
$var wire 32 " INSTRUCTION [31:0] $end
$var reg 1 # CLK $end
$var reg 1 $ RESET $end
$var integer 32 % i [31:0] $end
$scope module mycpu $end
$var wire 1 # CLK $end
$var wire 32 & INSTRUCTION [31:0] $end
$var wire 1 $ RESET $end
$var wire 1 ' pc_src $end
$var wire 1 ( zero $end
$var wire 1 ) writeenable $end
$var wire 8 * twos_result [7:0] $end
$var wire 2 + shift_sel [1:0] $end
$var wire 8 , regout2 [7:0] $end
$var wire 8 - regout1 [7:0] $end
$var wire 3 . rd [2:0] $end
$var wire 32 / pc_next [31:0] $end
$var wire 8 0 opcode [7:0] $end
$var wire 8 1 offset_imm [7:0] $end
$var wire 1 2 neg_sel $end
$var wire 1 3 jump $end
$var wire 1 4 imm_sel $end
$var wire 8 5 imm [7:0] $end
$var wire 32 6 extended_offset [31:0] $end
$var wire 1 7 branch_neq $end
$var wire 1 8 branch_eq $end
$var wire 32 9 bj_target [31:0] $end
$var wire 3 : aluop [2:0] $end
$var wire 8 ; alu_result [7:0] $end
$var reg 32 < PC [31:0] $end
$var reg 8 = alu_data2 [7:0] $end
$var reg 8 > mux_sub_out [7:0] $end
$var reg 3 ? read_reg1_addr [2:0] $end
$var reg 3 @ read_reg2_addr [2:0] $end
$scope module bja $end
$var wire 32 A OFFSET [31:0] $end
$var wire 32 B PC_NEXT [31:0] $end
$var reg 32 C TARGET [31:0] $end
$upscope $end
$scope module cu $end
$var wire 8 D OPCODE [7:0] $end
$var parameter 8 E OP_ADD $end
$var parameter 8 F OP_AND $end
$var parameter 8 G OP_BEQ $end
$var parameter 8 H OP_BNE $end
$var parameter 8 I OP_J $end
$var parameter 8 J OP_LOADI $end
$var parameter 8 K OP_MOV $end
$var parameter 8 L OP_MULT $end
$var parameter 8 M OP_OR $end
$var parameter 8 N OP_ROR $end
$var parameter 8 O OP_SLL $end
$var parameter 8 P OP_SRA $end
$var parameter 8 Q OP_SRL $end
$var parameter 8 R OP_SUB $end
$var reg 3 S ALUOP [2:0] $end
$var reg 1 8 BRANCH_EQ $end
$var reg 1 7 BRANCH_NEQ $end
$var reg 1 4 IMM_SEL $end
$var reg 1 3 JUMP $end
$var reg 1 2 NEG_SEL $end
$var reg 2 T SHIFT_SEL [1:0] $end
$var reg 1 ) WRITEENABLE $end
$upscope $end
$scope module main_alu $end
$var wire 8 U DATA2 [7:0] $end
$var wire 3 V SELECT [2:0] $end
$var wire 2 W SHIFT_SEL [1:0] $end
$var wire 8 X shift_res [7:0] $end
$var wire 8 Y or_res [7:0] $end
$var wire 8 Z mult_res [7:0] $end
$var wire 8 [ forward_res [7:0] $end
$var wire 8 \ and_res [7:0] $end
$var wire 8 ] add_res [7:0] $end
$var wire 8 ^ DATA1 [7:0] $end
$var reg 8 _ RESULT [7:0] $end
$var reg 1 ( ZERO $end
$scope module andu $end
$var wire 8 ` DATA2 [7:0] $end
$var wire 8 a DATA1 [7:0] $end
$var reg 8 b RESULT [7:0] $end
$upscope $end
$scope module au $end
$var wire 8 c DATA2 [7:0] $end
$var wire 8 d DATA1 [7:0] $end
$var reg 8 e RESULT [7:0] $end
$upscope $end
$scope module fu $end
$var wire 8 f DATA2 [7:0] $end
$var reg 8 g RESULT [7:0] $end
$upscope $end
$scope module mu $end
$var wire 8 h DATA2 [7:0] $end
$var wire 8 i p7 [7:0] $end
$var wire 8 j p6 [7:0] $end
$var wire 8 k p5 [7:0] $end
$var wire 8 l p4 [7:0] $end
$var wire 8 m p3 [7:0] $end
$var wire 8 n p2 [7:0] $end
$var wire 8 o p1 [7:0] $end
$var wire 8 p p0 [7:0] $end
$var wire 8 q DATA1 [7:0] $end
$var reg 8 r RESULT [7:0] $end
$upscope $end
$scope module ou $end
$var wire 8 s DATA2 [7:0] $end
$var wire 8 t DATA1 [7:0] $end
$var reg 8 u RESULT [7:0] $end
$upscope $end
$scope module su $end
$var wire 8 v DATA2 [7:0] $end
$var wire 2 w SHIFT_SEL [1:0] $end
$var wire 8 x sr3 [7:0] $end
$var wire 8 y sr2 [7:0] $end
$var wire 8 z sr1 [7:0] $end
$var wire 8 { sl3 [7:0] $end
$var wire 8 | sl2 [7:0] $end
$var wire 8 } sl1 [7:0] $end
$var wire 3 ~ shamt [2:0] $end
$var wire 8 !" sa3 [7:0] $end
$var wire 8 "" sa2 [7:0] $end
$var wire 8 #" sa1 [7:0] $end
$var wire 8 $" ro3 [7:0] $end
$var wire 8 %" ro2 [7:0] $end
$var wire 8 &" ro1 [7:0] $end
$var wire 8 '" DATA1 [7:0] $end
$var reg 8 (" RESULT [7:0] $end
$upscope $end
$upscope $end
$scope module pca $end
$var wire 32 )" PC_IN [31:0] $end
$var reg 32 *" PC_NEXT [31:0] $end
$upscope $end
$scope module rf $end
$var wire 1 # CLK $end
$var wire 8 +" IN [7:0] $end
$var wire 3 ," INADDRESS [2:0] $end
$var wire 3 -" OUT1ADDRESS [2:0] $end
$var wire 3 ." OUT2ADDRESS [2:0] $end
$var wire 1 $ RESET $end
$var wire 1 ) WRITE $end
$var reg 8 /" OUT1 [7:0] $end
$var reg 8 0" OUT2 [7:0] $end
$var integer 32 1" i [31:0] $end
$upscope $end
$scope module tc $end
$var wire 8 2" DATA [7:0] $end
$var reg 8 3" RESULT [7:0] $end
$upscope $end
$upscope $end
$upscope $end
$enddefinitions $end
$comment Show the parameter values. $end
$dumpall
b11 R
b1010 Q
b1011 P
b1001 O
b1100 N
b101 M
b1000 L
b1 K
b0 J
b110 I
b1101 H
b111 G
b100 F
b10 E
$end
#0
$dumpvars
bx 3"
bx 2"
bx 1"
bx 0"
bx /"
bx ."
bx -"
bx ,"
bx +"
bx *"
bx )"
bx ("
bx '"
bx &"
bx %"
bx $"
bx #"
bx ""
bx !"
bx ~
bx }
bx |
bx {
bx z
bx y
bx x
bx w
bx v
bx u
bx t
bx s
bx r
bx q
bx p
bx0 o
bx00 n
bx000 m
bx0000 l
bx00000 k
bx000000 j
bx0000000 i
bx h
bx g
bx f
bx e
bx d
bx c
bx b
bx a
bx `
bx _
bx ^
bx ]
bx \
bx [
bx Z
bx Y
bx X
bx W
bx V
bx U
bx T
bx S
bx D
bx C
bx B
bx00 A
bx @
bx ?
bx >
bx =
bx <
bx ;
bx :
bx 9
x8
x7
bx00 6
bx 5
x4
x3
x2
bx 1
bx 0
bx /
bx .
bx -
bx ,
bx +
bx *
x)
x(
x'
bx &
b10000000000 %
0$
0#
bx "
bx !
$end
#10
1$
#40
1#
#50
b0 !
b0 <
b0 )"
b1000 1"
#60
b100 /
b100 B
b100 *"
#70
b101 @
b101 ."
b0 ?
b0 -"
b0 0
b0 D
b1 .
b1 ,"
b10001101 5
b100 6
b100 A
b1 1
b10000000010001101 "
b10000000010001101 &
#80
bx0 |
b0xxxxxxx y
bx0 }
bx00000 {
b0xxxxxxx z
b0xxx x
b0 o
b0 l
b0 k
b0 j
0'
b101 ~
b10001101 =
b10001101 U
b10001101 `
b10001101 c
b10001101 f
b10001101 h
b10001101 s
b10001101 v
0(
0$
b0 +
b0 T
b0 W
b0 w
07
08
03
02
14
1)
b0 :
b0 S
b0 V
b1000 9
b1000 C
0#
#90
b0 $"
b0 !"
b0 x
b0 {
b0 %"
b0 ""
b0 y
b0 |
b0 &"
b0 #"
b0 z
b0 }
b0 i
b0 m
b0 n
b10001101 ;
b10001101 _
b10001101 +"
b0 >
b0 p
b10001101 Y
b10001101 u
b0 \
b0 b
b10001101 [
b10001101 g
bx00000 X
bx00000 ("
b0 ,
b0 0"
b0 2"
b0 -
b0 ^
b0 a
b0 d
b0 q
b0 t
b0 '"
b0 /"
#100
b0 X
b0 ("
b0 *
b0 3"
b0 Z
b0 r
b10001101 ]
b10001101 e
#120
1#
#130
b100 !
b100 <
b100 )"
#140
b1000 /
b1000 B
b1000 *"
#150
b10 ~
b10 =
b10 U
b10 `
b10 c
b10 f
b10 h
b10 s
b10 v
b10 @
b10 ."
b10 .
b10 ,"
b10 5
b1000 6
b1000 A
b10 1
b100000000000000010 "
b100000000000000010 &
#160
b10 ;
b10 _
b10 +"
b10 Y
b10 u
b10 [
b10 g
b10000 9
b10000 C
0#
#170
b10 ]
b10 e
#200
1#
#210
b1000 !
b1000 <
b1000 )"
#220
b1100 /
b1100 B
b1100 *"
#230
b10 >
b1 ?
b1 -"
b1000 0
b1000 D
b11 .
b11 ,"
b1100 6
b1100 A
b11 1
b10 ,
b10 0"
b10 2"
b1000000000110000000100000010 "
b1000000000110000000100000010 &
#240
1(
b0 ;
b0 _
b0 +"
b100 :
b100 S
b100 V
04
1)
b11111110 *
b11111110 3"
b11000 9
b11000 C
0#
#250
b1100011 $"
b11100011 !"
b100011 x
b110100 {
b1100011 %"
b11100011 ""
b100011 y
b110100 |
b11010 o
b10001101 &"
b10001101 #"
b10001101 z
b10001101 }
b10001101 -
b10001101 ^
b10001101 a
b10001101 d
b10001101 q
b10001101 t
b10001101 '"
b10001101 /"
#260
b110100 X
b110100 ("
b10001111 Y
b10001111 u
#270
0(
b11010 ;
b11010 _
b11010 +"
b11010 Z
b11010 r
b10001111 ]
b10001111 e
#280
1#
#290
b1100 !
b1100 <
b1100 )"
#300
b10000 /
b10000 B
b10000 *"
#310
b1001 0
b1001 D
b100 .
b100 ,"
b10000 6
b10000 A
b100 1
b1001000001000000000100000010 "
b1001000001000000000100000010 &
#320
b110100 ;
b110100 _
b110100 +"
14
1)
b101 :
b101 S
b101 V
b100000 9
b100000 C
0#
#360
1#
#370
b10000 !
b10000 <
b10000 )"
#380
b10100 /
b10100 B
b10100 *"
#390
b1010 0
b1010 D
b101 .
b101 ,"
b10100 6
b10100 A
b101 1
b1010000001010000000100000010 "
b1010000001010000000100000010 &
#400
b1 +
b1 T
b1 W
b1 w
14
1)
b101 :
b101 S
b101 V
b101000 9
b101000 C
0#
#410
b100011 ;
b100011 _
b100011 +"
b100011 X
b100011 ("
#440
1#
#450
b10100 !
b10100 <
b10100 )"
#460
b11000 /
b11000 B
b11000 *"
#470
b1011 0
b1011 D
b110 .
b110 ,"
b11000 6
b11000 A
b110 1
b1011000001100000000100000010 "
b1011000001100000000100000010 &
#480
b10 +
b10 T
b10 W
b10 w
14
1)
b101 :
b101 S
b101 V
b110000 9
b110000 C
0#
#490
b11100011 ;
b11100011 _
b11100011 +"
b11100011 X
b11100011 ("
#520
1#
#530
b11000 !
b11000 <
b11000 )"
#540
b11100 /
b11100 B
b11100 *"
#550
b1100 0
b1100 D
b111 .
b111 ,"
b11100 6
b11100 A
b111 1
b1100000001110000000100000010 "
b1100000001110000000100000010 &
#560
b11 +
b11 T
b11 W
b11 w
14
1)
b101 :
b101 S
b101 V
b111000 9
b111000 C
0#
#570
b1100011 ;
b1100011 _
b1100011 +"
b1100011 X
b1100011 ("
#600
1#
#610
b11100 !
b11100 <
b11100 )"
#620
b100000 /
b100000 B
b100000 *"
#630
b1101 0
b1101 D
b10 .
b10 ,"
b1000 6
b1000 A
b10 1
b1101000000100000000100000010 "
b1101000000100000000100000010 &
#640
b1000000 {
b10 x
b11111110 !"
b110110 $"
b110100 n
b1101000 m
b11010000 l
b10100000 k
b1000000 j
b10000000 i
b110 ~
1'
b11111110 =
b11111110 U
b11111110 `
b11111110 c
b11111110 f
b11111110 h
b11111110 s
b11111110 v
b11111110 >
b10001111 ;
b10001111 _
b10001111 +"
17
12
b0 +
b0 T
b0 W
b0 w
04
0)
b1 :
b1 S
b1 V
b101000 9
b101000 C
0#
#650
b10001100 \
b10001100 b
b11111111 Y
b11111111 u
b11111110 [
b11111110 g
b1000000 X
b1000000 ("
#660
b10001011 ;
b10001011 _
b10001011 +"
b10001011 ]
b10001011 e
b11100110 Z
b11100110 r
#680
1#
#690
b101000 !
b101000 <
b101000 )"
#700
b101100 /
b101100 B
b101100 *"
#710
b111 @
b111 ."
b0 ?
b0 -"
b0 0
b0 D
b0 .
b0 ,"
b11111111 5
b0 6
b0 A
b0 1
b11111111 "
b11111111 &
